DuIvyTools/__init__.py
DuIvyTools/DuIvyTools/DIT.py
DuIvyTools/DuIvyTools/__init__.py
DuIvyTools/DuIvyTools/utils.py
DuIvyTools/DuIvyTools/Commands/Commands.py
DuIvyTools/DuIvyTools/Commands/__init__.py
DuIvyTools/DuIvyTools/Commands/otherCommands.py
DuIvyTools/DuIvyTools/Commands/xpmCommands.py
DuIvyTools/DuIvyTools/Commands/xvgCommands.py
DuIvyTools/DuIvyTools/FileParser/__init__.py
DuIvyTools/DuIvyTools/FileParser/groParser.py
DuIvyTools/DuIvyTools/FileParser/mdpParser.py
DuIvyTools/DuIvyTools/FileParser/ndxParser.py
DuIvyTools/DuIvyTools/FileParser/pdbParser.py
DuIvyTools/DuIvyTools/FileParser/xpmParser.py
DuIvyTools/DuIvyTools/FileParser/xvgParser.py
DuIvyTools/DuIvyTools/Visualizer/Visualizer_gnuplot.py
DuIvyTools/DuIvyTools/Visualizer/Visualizer_matplotlib.py
DuIvyTools/DuIvyTools/Visualizer/Visualizer_plotext.py
DuIvyTools/DuIvyTools/Visualizer/Visualizer_plotly.py
DuIvyTools/DuIvyTools/Visualizer/__init__.py
DuIvyTools/DuIvyTools/data/gnuplotstyle/DIT.gpstyle
DuIvyTools/DuIvyTools/data/mdps/blank.mdp
DuIvyTools/DuIvyTools/data/mdps/em.mdp
DuIvyTools/DuIvyTools/data/mdps/ions.mdp
DuIvyTools/DuIvyTools/data/mdps/md.mdp
DuIvyTools/DuIvyTools/data/mdps/npt.mdp
DuIvyTools/DuIvyTools/data/mdps/nvt.mdp
DuIvyTools/DuIvyTools/data/mplstyle/DIT.mplstyle
DuIvyTools/DuIvyTools/data/mplstyle/blank.mplstyle
DuIvyTools/DuIvyTools/data/mplstyle/nature.mplstyle
DuIvyTools/DuIvyTools/data/mplstyle/science.mplstyle
DuIvyTools/DuIvyTools/data/plotlystyle/DIT.json
DuIvyTools/DuIvyTools/data/plotlystyle/bootstrap.json
DuIvyTools/DuIvyTools/data/plotlystyle/dit_ggplot2.json
DuIvyTools/DuIvyTools/data/plotlystyle/dit_plotly.json
DuIvyTools/DuIvyTools/data/plotlystyle/dit_seaborn.json
DuIvyTools/DuIvyTools/data/ramachandran/pref_general.data
DuIvyTools/DuIvyTools/data/ramachandran/pref_glycine.data
DuIvyTools/DuIvyTools/data/ramachandran/pref_preproline.data
DuIvyTools/DuIvyTools/data/ramachandran/pref_proline.data
DuIvyTools/DuIvyTools_old/DCCM.py
DuIvyTools/DuIvyTools_old/DIT.py
DuIvyTools-0.6.0.dist-info/LICENSE
DuIvyTools-0.6.0.dist-info/METADATA
DuIvyTools-0.6.0.dist-info/WHEEL
DuIvyTools-0.6.0.dist-info/entry_points.txt
DuIvyTools-0.6.0.dist-info/top_level.txt
DuIvyTools-0.6.0.dist-info/RECORD
