Metadata-Version: 2.1
Name: DuIvyTools
Version: 0.6.0
Summary: A simple tool for GROMACS results analysis and visualization
Home-page: https://github.com/CharlesHahn/DuIvyTools
Download-URL: https://github.com/CharlesHahn/DuIvyTools
Author: CharlesHahn,杜艾维
Author-email: 
Platform: cross-platform
Classifier: Development Status :: 5 - Production/Stable
Classifier: License :: OSI Approved :: GNU General Public License v3 (GPLv3)
Classifier: Programming Language :: Python
Classifier: Programming Language :: Python :: 3
Classifier: Topic :: Scientific/Engineering :: Bio-Informatics
Classifier: Topic :: Scientific/Engineering :: Chemistry
Classifier: Intended Audience :: Science/Research
License-File: LICENSE
Requires-Dist: matplotlib
Requires-Dist: plotly
Requires-Dist: numpy
Requires-Dist: pandas
Requires-Dist: scipy
Requires-Dist: argparse
Requires-Dist: colorama
Requires-Dist: plotext
Provides-Extra: test
Requires-Dist: matplotlib ; extra == 'test'
Requires-Dist: plotly ; extra == 'test'
Requires-Dist: numpy ; extra == 'test'
Requires-Dist: pandas ; extra == 'test'
Requires-Dist: scipy ; extra == 'test'
Requires-Dist: argparse ; extra == 'test'
Requires-Dist: colorama ; extra == 'test'
Requires-Dist: plotext ; extra == 'test'
